missinglink/__init__.py
missinglink/sdk/__init__.py
missinglink/sdk/conda_util.py
missinglink/sdk/pip_util.py
missinglink/sdk/pkg_provider.py
missinglink/sdk/print_or_log.py
missinglink_sdk-19.9.26893.dist-info/LICENSE
missinglink_sdk-19.9.26893.dist-info/METADATA
missinglink_sdk-19.9.26893.dist-info/WHEEL
missinglink_sdk-19.9.26893.dist-info/top_level.txt
missinglink_sdk-19.9.26893.dist-info/RECORD
