Metadata-Version: 2.1
Name: missinglink-sdk
Version: 19.9.26893
Summary: SDK for streaming realtime metrics to https://missinglink.ai
Home-page: UNKNOWN
Author: MissingLink.ai
Author-email: support@missinglink.ai
License: mit
Keywords: prod
Platform: any
Requires-Dist: missinglink-kernel (==19.9.26893)
